[{"_id":1553836264517,"conditionsOperator":"and","conditions":[{"property":"type","operator":"=","value":"account"}],"component":"vertex","target":"vertex","properties":{"colors":["red"],"sizes":[16],"icons":["fa-address-card-o"],"iconColors":["rgb(255, 255, 255)"],"label":["account_no"]}},{"_id":1553836346451,"conditionsOperator":"and","conditions":[{"property":"type","operator":"=","value":"customer"}],"component":"vertex","target":"vertex","properties":{"colors":["rgb(21, 0, 255)"],"sizes":[16],"icons":["fa-user-man"],"iconColors":["white"],"label":["name"]}},{"_id":1553836414230,"conditionsOperator":"and","conditions":[{"property":"type","operator":"=","value":"merchant"}],"component":"vertex","target":"vertex","properties":{"colors":["rgb(3, 173, 11)"],"sizes":[16],"icons":["fa-shopping-cart"],"iconColors":["white"],"label":["name"]}},{"_id":1553836846437,"conditionsOperator":"and","conditions":[{"property":"type","operator":"=","value":"account"},{"property":"account_no","operator":"~","value":"xxx-zzz."}],"component":"vertex","target":"vertex","properties":{"colors":["rgb(255, 162, 0)"],"sizes":[16],"icons":["fa-address-card-o"],"iconColors":["white"],"label":["account_no"]}},{"_id":1554773861505,"conditionsOperator":"and","conditions":[],"component":"edge","target":"edge","properties":{"label":["label"]}}]